metaapi/__init__.py
metavoidapi-1.0.8.dist-info/LICENSE
metavoidapi-1.0.8.dist-info/METADATA
metavoidapi-1.0.8.dist-info/WHEEL
metavoidapi-1.0.8.dist-info/top_level.txt
metavoidapi-1.0.8.dist-info/RECORD
