Metadata-Version: 2.1
Name: metavoidapi
Version: 1.0.8
Summary: Metavoid Api Wrapper
Home-page: https://github.com/metavoidteam/metavoidapi-py.git
Author: metavoid
Author-email: metavoidteam@gmail.com
License: License :: OSI Approved :: GNU Lesser General Public License v3 (LGPLv3)
Classifier: Programming Language :: Python :: 3
Classifier: Programming Language :: Python :: 3.6
Classifier: Programming Language :: Python :: 3.7
Classifier: Programming Language :: Python :: 3.8
Classifier: Programming Language :: Python :: 3.9
Classifier: Operating System :: OS Independent
Requires-Python: >=3.6
License-File: LICENSE
Requires-Dist: requests
